Metadata-Version: 2.1
Name: tadkit-core
Version: 1.1.0
Summary: Unified interface for time series anomaly detection
Project-URL: Homepage, https://irt-systemx.github.io/tadkit-core
Project-URL: Documentation, https://irt-systemx.github.io/tadkit-core
Project-URL: Repository, https://github.com/IRT-SystemX/tadkit-core
Requires-Python: >=3.12
License-File: LICENSE
Requires-Dist: numpy>=1.26.0
Requires-Dist: pandas>=2.1.1
Requires-Dist: scikit-learn>=1.3.1
Requires-Dist: matplotlib>=3.8.0
Requires-Dist: ipywidgets>=7.7.5
Requires-Dist: nbformat>=4.2.0
Requires-Dist: plotly>=6.0.0
